k8scheck/__init__.py
k8scheck/client.py
k8scheck/condition.py
k8scheck/errors.py
k8scheck/manager.py
k8scheck/manifest.py
k8scheck/markers.py
k8scheck/plugin.py
k8scheck/response.py
k8scheck/utils.py
k8scheck/objects/__init__.py
k8scheck/objects/api_object.py
k8scheck/objects/clusterrolebinding.py
k8scheck/objects/configmap.py
k8scheck/objects/container.py
k8scheck/objects/daemonset.py
k8scheck/objects/deployment.py
k8scheck/objects/endpoints.py
k8scheck/objects/event.py
k8scheck/objects/ingress.py
k8scheck/objects/namespace.py
k8scheck/objects/networkpolicy.py
k8scheck/objects/node.py
k8scheck/objects/persistentvolumeclaim.py
k8scheck/objects/pod.py
k8scheck/objects/replicaset.py
k8scheck/objects/rolebinding.py
k8scheck/objects/secret.py
k8scheck/objects/service.py
k8scheck/objects/serviceaccount.py
k8scheck/objects/statefulset.py
k8scheck-0.9.11.dist-info/LICENSE
k8scheck-0.9.11.dist-info/METADATA
k8scheck-0.9.11.dist-info/WHEEL
k8scheck-0.9.11.dist-info/entry_points.txt
k8scheck-0.9.11.dist-info/top_level.txt
k8scheck-0.9.11.dist-info/RECORD
