Metadata-Version: 2.1
Name: k8scheck
Version: 0.9.11
Summary: A Kubernetes integration test framework in Python.
Home-page: https://github.com/3sIT/k8scheck
Author: Terry Drisi (originally Vapor IO)
Author-email: k8scheck@3si.me
License: GNU General Public License v3.0
Classifier: Environment :: Plugins
Classifier: Framework :: Pytest
Classifier: Intended Audience :: Developers
Classifier: Natural Language :: English
Classifier: Programming Language :: Python
Classifier: Programming Language :: Python :: 3
Classifier: Programming Language :: Python :: 3.7
Classifier: Programming Language :: Python :: 3.8
Classifier: Programming Language :: Python :: 3.9
Classifier: Programming Language :: Python :: 3.10
Classifier: Programming Language :: Python :: 3.11
Requires-Python: >=3.6
License-File: LICENSE
Requires-Dist: kubernetes (>=18.0.0)
Requires-Dist: pyyaml (>=4.2b1)
Requires-Dist: pytest
